finogeeks/__init__.py
finogeeks/dataflow.py
finogeeks-0.1.9.dist-info/DESCRIPTION.rst
finogeeks-0.1.9.dist-info/METADATA
finogeeks-0.1.9.dist-info/RECORD
finogeeks-0.1.9.dist-info/WHEEL
finogeeks-0.1.9.dist-info/metadata.json
finogeeks-0.1.9.dist-info/top_level.txt
