Metadata-Version: 2.0
Name: finogeeks
Version: 0.1.9
Summary: Private purpose package for finogeeks
Home-page: UNKNOWN
Author: UNKNOWN
Author-email: UNKNOWN
License: UNKNOWN
Platform: UNKNOWN
Requires-Dist: pymongo
Requires-Dist: kafka
